deltamemory/__init__.py
deltamemory/client.py
deltamemory/errors.py
deltamemory/py.typed
deltamemory/types.py
deltamemory-0.1.0.dist-info/METADATA
deltamemory-0.1.0.dist-info/WHEEL
deltamemory-0.1.0.dist-info/RECORD
