Metadata-Version: 2.4
Name: deltamemory
Version: 0.1.0
Summary: Python SDK for DeltaMemory - Smart memory database for AI agents
Project-URL: Homepage, https://github.com/bikidsx/deltamemory
Project-URL: Repository, https://github.com/bikidsx/deltamemory
Project-URL: Documentation, https://github.com/bikidsx/deltamemory#readme
Author: DeltaMemory Team
License-Expression: Apache-2.0
Keywords: ai,cognitivedb,database,deltamemory,embeddings,events,knowledge-graph,llm,memory,profiles,vector
Classifier: Development Status :: 4 - Beta
Classifier: Intended Audience :: Developers
Classifier: License :: OSI Approved :: Apache Software License
Classifier: Programming Language :: Python :: 3
Classifier: Programming Language :: Python :: 3.10
Classifier: Programming Language :: Python :: 3.11
Classifier: Programming Language :: Python :: 3.12
Classifier: Topic :: Database
Classifier: Topic :: Scientific/Engineering :: Artificial Intelligence
Classifier: Typing :: Typed
Requires-Python: >=3.10
Requires-Dist: httpx>=0.25.0
Provides-Extra: dev
Requires-Dist: mypy>=1.0.0; extra == 'dev'
Requires-Dist: pytest-asyncio>=0.21.0; extra == 'dev'
Requires-Dist: pytest>=7.0.0; extra == 'dev'
Requires-Dist: ruff>=0.1.0; extra == 'dev'
